[
  {
    "id": "f7e4d1cd-b1e8-4e1b-8175-3a3a855f9617",
    "data": [
      {
        "text": "Yep",
        "userDefined": false
      }
    ],
    "isTemplate": false,
    "count": 0,
    "updated": 1529337423
  },
  {
    "id": "b3f90bfa-c3ba-40fe-9f71-a0439add11d7",
    "data": [
      {
        "text": "Yup",
        "userDefined": false
      }
    ],
    "isTemplate": false,
    "count": 0,
    "updated": 1529337423
  },
  {
    "id": "da3abdc7-9919-49e8-8f20-03c410d22ad5",
    "data": [
      {
        "text": "Yeah",
        "userDefined": false
      }
    ],
    "isTemplate": false,
    "count": 0,
    "updated": 1529337423
  },
  {
    "id": "011a965e-951e-4d53-9669-5a4ac67dcf9e",
    "data": [
      {
        "text": "okay",
        "userDefined": false
      }
    ],
    "isTemplate": false,
    "count": 0,
    "updated": 1529337423
  },
  {
    "id": "747483f9-76bd-450f-a7f2-ea04b2e7aa91",
    "data": [
      {
        "text": "sounds good",
        "userDefined": false
      }
    ],
    "isTemplate": false,
    "count": 0,
    "updated": 1529337423
  },
  {
    "id": "0a8ff066-9b77-448d-a4e7-1825ad52d9b5",
    "data": [
      {
        "text": "yes",
        "userDefined": false
      }
    ],
    "isTemplate": false,
    "count": 0,
    "updated": 1529337423
  },
  {
    "id": "5be1e4e3-2f1a-41df-912b-cedfafdbc617",
    "data": [
      {
        "text": "exactly",
        "userDefined": false
      }
    ],
    "isTemplate": false,
    "count": 0,
    "updated": 1529337423
  },
  {
    "id": "e427ca6f-b62d-43b4-a4b0-46bc34e88be0",
    "data": [
      {
        "text": "ok",
        "userDefined": false
      }
    ],
    "isTemplate": false,
    "count": 0,
    "updated": 1529337423
  },
  {
    "id": "be3bc8a6-a834-4fe9-9a4c-953e84e6a1f0",
    "data": [
      {
        "text": "that\u0027s correct",
        "userDefined": false
      }
    ],
    "isTemplate": false,
    "count": 0,
    "updated": 1529337423
  },
  {
    "id": "db1b07c1-8ebb-4a1f-a41c-8fac4bce25e7",
    "data": [
      {
        "text": "sure",
        "userDefined": false
      }
    ],
    "isTemplate": false,
    "count": 2,
    "updated": 1529337423
  },
  {
    "id": "174c3eb8-5607-4474-87d4-95b2b4af5808",
    "data": [
      {
        "text": "do it",
        "userDefined": false
      }
    ],
    "isTemplate": false,
    "count": 1,
    "updated": 1529337423
  },
  {
    "id": "5c889165-e38e-46bf-8542-0a15a3f3fd1c",
    "data": [
      {
        "text": "confirm",
        "userDefined": false
      }
    ],
    "isTemplate": false,
    "count": 2,
    "updated": 1529337423
  },
  {
    "id": "c62455db-1312-4628-976e-d264ff7aa7f0",
    "data": [
      {
        "text": "I agree",
        "userDefined": false
      }
    ],
    "isTemplate": false,
    "count": 1,
    "updated": 1529337423
  },
  {
    "id": "b9800003-b498-4d6a-bc13-96f7e9849537",
    "data": [
      {
        "text": "I don\u0027t mind",
        "userDefined": false
      }
    ],
    "isTemplate": false,
    "count": 0,
    "updated": 1529337423
  },
  {
    "id": "ac4d6930-fd68-4f80-a281-24dad63ec990",
    "data": [
      {
        "text": "of course",
        "userDefined": false
      }
    ],
    "isTemplate": false,
    "count": 0,
    "updated": 1529337423
  }
]